victor/__init__.py
victor/agent/__init__.py
victor/agent/action_authorizer.py
victor/agent/adaptive_mode_controller.py
victor/agent/argument_normalizer.py
victor/agent/auto_commit.py
victor/agent/background_agent.py
victor/agent/budget_manager.py
victor/agent/capability_registry.py
victor/agent/change_tracker.py
victor/agent/checkpoints.py
victor/agent/chunk_generator.py
victor/agent/code_correction_middleware.py
victor/agent/complexity_classifier.py
victor/agent/config_loader.py
victor/agent/context_compactor.py
victor/agent/context_reminder.py
victor/agent/continuation_strategy.py
victor/agent/conversation_controller.py
victor/agent/conversation_embedding_store.py
victor/agent/conversation_export.py
victor/agent/conversation_memory.py
victor/agent/conversation_state.py
victor/agent/debug_logger.py
victor/agent/error_recovery.py
victor/agent/grounding_verifier.py
victor/agent/intelligent_pipeline.py
victor/agent/intelligent_prompt_builder.py
victor/agent/loop_detector.py
victor/agent/mcp_connector.py
victor/agent/message_history.py
victor/agent/metrics_collector.py
victor/agent/middleware_chain.py
victor/agent/milestone_monitor.py
victor/agent/mode_controller.py
victor/agent/mode_workflow_team_coordinator.py
victor/agent/model_switcher.py
victor/agent/observability.py
victor/agent/orchestrator.py
victor/agent/orchestrator_factory.py
victor/agent/orchestrator_integration.py
victor/agent/orchestrator_recovery.py
victor/agent/orchestrator_utils.py
victor/agent/output_aggregator.py
victor/agent/output_deduplicator.py
victor/agent/parallel_executor.py
victor/agent/parameter_enforcer.py
victor/agent/performance_profiler.py
victor/agent/plugin_loader.py
victor/agent/prompt_builder.py
victor/agent/prompt_coordinator.py
victor/agent/prompt_corpus_data.py
victor/agent/prompt_corpus_registry.py
victor/agent/prompt_requirement_extractor.py
victor/agent/protocols.py
victor/agent/provider_manager.py
victor/agent/provider_tool_guidance.py
victor/agent/read_cache.py
victor_ai-0.3.0.dist-info/licenses/LICENSE
victor_ai-0.3.0.dist-info/METADATA
victor_ai-0.3.0.dist-info/WHEEL
victor_ai-0.3.0.dist-info/entry_points.txt
victor_ai-0.3.0.dist-info/top_level.txt
victor_ai-0.3.0.dist-info/RECORD
