Metadata-Version: 2.4
Name: victor-ai
Version: 0.3.0
Summary: Enterprise-Ready AI Coding Assistant - Code to Victory with Any AI
Author-email: Vijaykumar Singh <singhvjd@gmail.com>
License: Apache-2.0
Project-URL: Homepage, https://github.com/vijayksingh/victor
Project-URL: Documentation, https://github.com/vijayksingh/victor#readme
Project-URL: Repository, https://github.com/vijayksingh/victor
Project-URL: Issues, https://github.com/vijayksingh/victor/issues
Keywords: ai,llm,coding-agent,victor,anthropic,openai,ollama,claude,gpt,cli,terminal
Classifier: Development Status :: 3 - Alpha
Classifier: Intended Audience :: Developers
Classifier: License :: OSI Approved :: Apache Software License
Classifier: Programming Language :: Python :: 3
Classifier: Programming Language :: Python :: 3.10
Classifier: Programming Language :: Python :: 3.11
Classifier: Programming Language :: Python :: 3.12
Classifier: Topic :: Software Development :: Libraries :: Python Modules
Classifier: Topic :: Scientific/Engineering :: Artificial Intelligence
Requires-Python: >=3.10
License-File: LICENSE
Requires-Dist: pydantic>=2.0
Requires-Dist: pydantic-settings>=2.0
Requires-Dist: python-dotenv>=1.0
Requires-Dist: typing_extensions>=4.0
Requires-Dist: httpx>=0.27
Requires-Dist: aiofiles>=23.0
Requires-Dist: aiohttp>=3.9
Requires-Dist: typer>=0.12
Requires-Dist: rich>=13.7
Requires-Dist: prompt-toolkit>=3.0
Requires-Dist: textual>=0.89
Requires-Dist: anthropic>=0.34
Requires-Dist: openai>=1.40
Requires-Dist: gitpython>=3.1
Requires-Dist: jsonschema>=4.20
Requires-Dist: tiktoken>=0.7
Requires-Dist: pyyaml>=6.0
Requires-Dist: beautifulsoup4>=4.12
Requires-Dist: lxml>=5.0
Requires-Dist: tree-sitter>=0.23
Requires-Dist: pygments>=2.17
Requires-Dist: tree-sitter-python>=0.23
Requires-Dist: tree-sitter-javascript>=0.23
Requires-Dist: tree-sitter-typescript>=0.23
Requires-Dist: tree-sitter-go>=0.23
Requires-Dist: tree-sitter-rust>=0.23
Requires-Dist: tree-sitter-java>=0.23
Requires-Dist: tree-sitter-cpp>=0.23
Requires-Dist: cachetools>=5.3
Requires-Dist: diskcache>=5.6
Requires-Dist: docker>=7.0
Requires-Dist: docstring-parser>=0.15
Requires-Dist: sentence-transformers>=2.2.0
Requires-Dist: lancedb>=0.6.0
Requires-Dist: pyarrow>=14.0
Provides-Extra: dev
Requires-Dist: pytest>=8.0; extra == "dev"
Requires-Dist: pytest-asyncio>=0.23; extra == "dev"
Requires-Dist: pytest-cov>=4.1; extra == "dev"
Requires-Dist: pytest-mock>=3.12; extra == "dev"
Requires-Dist: pytest-json-report>=1.5.0; extra == "dev"
Requires-Dist: respx>=0.21; extra == "dev"
Requires-Dist: ruff>=0.5; extra == "dev"
Requires-Dist: mypy>=1.10; extra == "dev"
Requires-Dist: black>=24.0; extra == "dev"
Requires-Dist: types-pyyaml; extra == "dev"
Requires-Dist: types-aiofiles; extra == "dev"
Provides-Extra: docs
Requires-Dist: mkdocs>=1.5; extra == "docs"
Requires-Dist: mkdocs-material>=9.5; extra == "docs"
Requires-Dist: mkdocstrings[python]>=0.24; extra == "docs"
Provides-Extra: build
Requires-Dist: pyinstaller>=6.0; extra == "build"
Requires-Dist: pyinstaller-hooks-contrib>=2024.0; extra == "build"
Provides-Extra: api
Requires-Dist: fastapi>=0.109; extra == "api"
Requires-Dist: uvicorn>=0.27; extra == "api"
Provides-Extra: checkpoints
Requires-Dist: aiosqlite>=0.19; extra == "checkpoints"
Provides-Extra: google
Requires-Dist: google-genai>=1.0; extra == "google"
Provides-Extra: lang-c
Requires-Dist: tree-sitter-c>=0.23; extra == "lang-c"
Provides-Extra: lang-csharp
Requires-Dist: tree-sitter-c-sharp>=0.23; extra == "lang-csharp"
Provides-Extra: lang-ruby
Requires-Dist: tree-sitter-ruby>=0.23; extra == "lang-ruby"
Provides-Extra: lang-php
Requires-Dist: tree-sitter-php>=0.24; extra == "lang-php"
Provides-Extra: lang-swift
Requires-Dist: tree-sitter-swift>=0.0.1; extra == "lang-swift"
Provides-Extra: lang-scala
Requires-Dist: tree-sitter-scala>=0.23; extra == "lang-scala"
Provides-Extra: lang-kotlin
Requires-Dist: tree-sitter-kotlin>=1.0; extra == "lang-kotlin"
Provides-Extra: lang-bash
Requires-Dist: tree-sitter-bash>=0.23; extra == "lang-bash"
Provides-Extra: lang-lua
Requires-Dist: tree-sitter-lua>=0.2; extra == "lang-lua"
Provides-Extra: lang-elixir
Requires-Dist: tree-sitter-elixir>=0.3; extra == "lang-elixir"
Provides-Extra: lang-haskell
Requires-Dist: tree-sitter-haskell>=0.23; extra == "lang-haskell"
Provides-Extra: lang-sql
Requires-Dist: tree-sitter-sql>=0.3; extra == "lang-sql"
Provides-Extra: lang-html
Requires-Dist: tree-sitter-html>=0.23; extra == "lang-html"
Provides-Extra: lang-css
Requires-Dist: tree-sitter-css>=0.23; extra == "lang-css"
Provides-Extra: lang-json
Requires-Dist: tree-sitter-json>=0.23; extra == "lang-json"
Provides-Extra: lang-yaml
Requires-Dist: tree-sitter-yaml>=0.6; extra == "lang-yaml"
Provides-Extra: lang-toml
Requires-Dist: tree-sitter-toml>=0.6; extra == "lang-toml"
Provides-Extra: lang-markdown
Requires-Dist: tree-sitter-markdown>=0.5; extra == "lang-markdown"
Provides-Extra: lang-xml
Requires-Dist: tree-sitter-xml>=0.6; extra == "lang-xml"
Provides-Extra: lang-web
Requires-Dist: tree-sitter-html>=0.23; extra == "lang-web"
Requires-Dist: tree-sitter-css>=0.23; extra == "lang-web"
Requires-Dist: tree-sitter-json>=0.23; extra == "lang-web"
Requires-Dist: tree-sitter-javascript>=0.23; extra == "lang-web"
Requires-Dist: tree-sitter-typescript>=0.23; extra == "lang-web"
Provides-Extra: lang-config
Requires-Dist: tree-sitter-json>=0.23; extra == "lang-config"
Requires-Dist: tree-sitter-yaml>=0.6; extra == "lang-config"
Requires-Dist: tree-sitter-toml>=0.6; extra == "lang-config"
Requires-Dist: tree-sitter-xml>=0.6; extra == "lang-config"
Requires-Dist: tree-sitter-markdown>=0.5; extra == "lang-config"
Provides-Extra: lang-jvm
Requires-Dist: tree-sitter-scala>=0.23; extra == "lang-jvm"
Requires-Dist: tree-sitter-kotlin>=1.0; extra == "lang-jvm"
Requires-Dist: tree-sitter-java>=0.23; extra == "lang-jvm"
Provides-Extra: lang-systems
Requires-Dist: tree-sitter-c>=0.23; extra == "lang-systems"
Requires-Dist: tree-sitter-bash>=0.23; extra == "lang-systems"
Requires-Dist: tree-sitter-cpp>=0.23; extra == "lang-systems"
Provides-Extra: lang-apple
Requires-Dist: tree-sitter-swift>=0.0.1; extra == "lang-apple"
Provides-Extra: lang-dotnet
Requires-Dist: tree-sitter-c-sharp>=0.23; extra == "lang-dotnet"
Provides-Extra: lang-scripting
Requires-Dist: tree-sitter-ruby>=0.23; extra == "lang-scripting"
Requires-Dist: tree-sitter-php>=0.24; extra == "lang-scripting"
Requires-Dist: tree-sitter-lua>=0.2; extra == "lang-scripting"
Provides-Extra: lang-functional
Requires-Dist: tree-sitter-elixir>=0.3; extra == "lang-functional"
Requires-Dist: tree-sitter-haskell>=0.23; extra == "lang-functional"
Requires-Dist: tree-sitter-scala>=0.23; extra == "lang-functional"
Provides-Extra: lang-all
Requires-Dist: tree-sitter-c>=0.23; extra == "lang-all"
Requires-Dist: tree-sitter-c-sharp>=0.23; extra == "lang-all"
Requires-Dist: tree-sitter-ruby>=0.23; extra == "lang-all"
Requires-Dist: tree-sitter-php>=0.24; extra == "lang-all"
Requires-Dist: tree-sitter-swift>=0.0.1; extra == "lang-all"
Requires-Dist: tree-sitter-scala>=0.23; extra == "lang-all"
Requires-Dist: tree-sitter-kotlin>=1.0; extra == "lang-all"
Requires-Dist: tree-sitter-bash>=0.23; extra == "lang-all"
Requires-Dist: tree-sitter-lua>=0.2; extra == "lang-all"
Requires-Dist: tree-sitter-elixir>=0.3; extra == "lang-all"
Requires-Dist: tree-sitter-haskell>=0.23; extra == "lang-all"
Requires-Dist: tree-sitter-sql>=0.3; extra == "lang-all"
Requires-Dist: tree-sitter-html>=0.23; extra == "lang-all"
Requires-Dist: tree-sitter-css>=0.23; extra == "lang-all"
Requires-Dist: tree-sitter-json>=0.23; extra == "lang-all"
Requires-Dist: tree-sitter-yaml>=0.6; extra == "lang-all"
Requires-Dist: tree-sitter-toml>=0.6; extra == "lang-all"
Requires-Dist: tree-sitter-markdown>=0.5; extra == "lang-all"
Requires-Dist: tree-sitter-xml>=0.6; extra == "lang-all"
Provides-Extra: native
Requires-Dist: maturin>=1.4; extra == "native"
Provides-Extra: all
Requires-Dist: victor[build,dev,docs,lang-all]; extra == "all"
Dynamic: license-file
